sqlite_column_sentry/__init__.py
sqlite_column_sentry/main.py
sqlite_column_sentry/prompts.py
sqlite_column_sentry-2025.12.21152531.dist-info/METADATA
sqlite_column_sentry-2025.12.21152531.dist-info/WHEEL
sqlite_column_sentry-2025.12.21152531.dist-info/top_level.txt
sqlite_column_sentry-2025.12.21152531.dist-info/RECORD
