Metadata-Version: 2.4
Name: sqlite-column-sentry
Version: 2025.12.21152531
Summary: A new package that helps developers ensure column safety in SQLite queries by analyzing and validating their SQL statements. The package takes a user's SQL query as text input and returns a structured
Author-email: sqlite-column-sentry <hi@eugene.plus>
License: MIT
Project-URL: Homepage, https://github.com/chigwell/sqlite-column-sentry
Requires-Python: >=3.9
Requires-Dist: langchain-llm7>=0.0.0
Requires-Dist: llmatch-messages>=0.0.0
Requires-Dist: langchain-core>=0.3.0
